{
    "transcripts_id": "ES2002a",
    "general_query_list": [
        {
            "query": "Summarize the whole meeting.",
            "oracle_info": [
                {
                    "turn_index": 0,
                    "sent_index": 2,
                    "speaker": "Project Manager",
                    "content": "{vocalsound} Um well this is the kick-off meeting for our our project ."
                },
                {
                    "turn_index": 0,
                    "sent_index": 5,
                    "speaker": "Project Manager",
                    "content": "Um so first of all , just to kind of make sure that we all know each other ,"
                },
                {
                    "turn_index": 2,
                    "sent_index": 0,
                    "speaker": "Project Manager",
                    "content": "I'm Laura and I'm the project manager ."
                },
                {
                    "turn_index": 12,
                    "sent_index": 0,
                    "speaker": "Industrial Designer",
                    "content": "Designing a remote control ."
                },
                {
                    "turn_index": 26,
                    "sent_index": 2,
                    "speaker": "Marketing",
                    "content": "My favourite animal is like {disfmarker}"
                },
                {
                    "turn_index": 206,
                    "sent_index": 1,
                    "speaker": "Marketing",
                    "content": "part ."
                }
            ]
        }
    ],
    "specific_query_list": [
        {
            "query": "Summarize the groupmates' self-introduction and the project introduction.",
            "oracle_info": [
                {
                    "turn_index": 0,
                    "sent_index": 2,
                    "speaker": "Project Manager",
                    "content": "{vocalsound} Um well this is the kick-off meeting for our our project ."
                },
                {
                    "turn_index": 0,
                    "sent_index": 5,
                    "speaker": "Project Manager",
                    "content": "Um so first of all , just to kind of make sure that we all know each other ,"
                },
                {
                    "turn_index": 2,
                    "sent_index": 0,
                    "speaker": "Project Manager",
                    "content": "I'm Laura and I'm the project manager ."
                },
                {
                    "turn_index": 12,
                    "sent_index": 0,
                    "speaker": "Industrial Designer",
                    "content": "Designing a remote control ."
                },
                {
                    "turn_index": 16,
                    "sent_index": 0,
                    "speaker": "Project Manager",
                    "content": "Is that what everybody got ?"
                }
            ]
        },
        {
            "query": "Summarize the job role for each groupmate.",
            "oracle_info": [
                {
                    "turn_index": 0,
                    "sent_index": 5,
                    "speaker": "Project Manager",
                    "content": "Um so first of all , just to kind of make sure that we all know each other ,"
                },
                {
                    "turn_index": 2,
                    "sent_index": 0,
                    "speaker": "Project Manager",
                    "content": "I'm Laura and I'm the project manager ."
                },
                {
                    "turn_index": 4,
                    "sent_index": 0,
                    "speaker": "Industrial Designer",
                    "content": "Hi , I'm David and I'm supposed to be an industrial designer ."
                },
                {
                    "turn_index": 6,
                    "sent_index": 0,
                    "speaker": "Marketing",
                    "content": "And I'm Andrew and I'm uh our marketing"
                },
                {
                    "turn_index": 7,
                    "sent_index": 0,
                    "speaker": "User Interface",
                    "content": "Um I'm Craig and I'm User Interface ."
                },
                {
                    "turn_index": 8,
                    "sent_index": 0,
                    "speaker": "Marketing",
                    "content": "expert ."
                }
            ]
        },
        {
            "query": "What did the group discuss about the email they received on the project announcement?",
            "oracle_info": [
                {
                    "turn_index": 9,
                    "sent_index": 7,
                    "speaker": "Project Manager",
                    "content": "Um , as you can see it's supposed to be original , trendy and user friendly ."
                },
                {
                    "turn_index": 9,
                    "sent_index": 9,
                    "speaker": "Project Manager",
                    "content": "Um and so there are three different stages to the design ."
                },
                {
                    "turn_index": 12,
                    "sent_index": 0,
                    "speaker": "Industrial Designer",
                    "content": "Designing a remote control ."
                }
            ]
        },
        {
            "query": "Summarize the discussion about the favourite animal characteristics and the workflow.",
            "oracle_info": [
                {
                    "turn_index": 51,
                    "sent_index": 0,
                    "speaker": "Marketing",
                    "content": "I coulda told you a whole lot more about beagles ."
                },
                {
                    "turn_index": 66,
                    "sent_index": 0,
                    "speaker": "Industrial Designer",
                    "content": "so um fish was a natural choice ."
                },
                {
                    "turn_index": 66,
                    "sent_index": 3,
                    "speaker": "Industrial Designer",
                    "content": "They come in and go {vocalsound} eat everything in sight . {vocalsound}"
                },
                {
                    "turn_index": 69,
                    "sent_index": 0,
                    "speaker": "Industrial Designer",
                    "content": "And they're quite harmless and mild and interesting ."
                },
                {
                    "turn_index": 79,
                    "sent_index": 0,
                    "speaker": "Marketing",
                    "content": "I see a dog in there ."
                },
                {
                    "turn_index": 92,
                    "sent_index": 0,
                    "speaker": "Project Manager",
                    "content": "Um he's very friendly and cheery and always pleased to see you ,"
                },
                {
                    "turn_index": 109,
                    "sent_index": 2,
                    "speaker": "Project Manager",
                    "content": "Okay , uh we now need to discuss the project finance ."
                },
                {
                    "turn_index": 109,
                    "sent_index": 5,
                    "speaker": "Project Manager",
                    "content": "Um so we're gonna be selling this on an international scale ."
                },
                {
                    "turn_index": 139,
                    "sent_index": 0,
                    "speaker": "Project Manager",
                    "content": "Yeah , yeah ."
                },
                {
                    "turn_index": 173,
                    "sent_index": 0,
                    "speaker": "Project Manager",
                    "content": "wouldn't it ,"
                },
                {
                    "turn_index": 202,
                    "sent_index": 3,
                    "speaker": "Marketing",
                    "content": "So they w all work actually function together"
                },
                {
                    "turn_index": 209,
                    "sent_index": 0,
                    "speaker": "Project Manager",
                    "content": "You keep losing them ."
                },
                {
                    "turn_index": 239,
                    "sent_index": 1,
                    "speaker": "Project Manager",
                    "content": "Well I guess that's up to our industrial designer ."
                },
                {
                    "turn_index": 250,
                    "sent_index": 2,
                    "speaker": "Project Manager",
                    "content": "the next meeting's gonna be in thirty minutes ."
                },
                {
                    "turn_index": 269,
                    "sent_index": 0,
                    "speaker": "Industrial Designer",
                    "content": "I think one factor would be production cost ."
                },
                {
                    "turn_index": 271,
                    "sent_index": 0,
                    "speaker": "Industrial Designer",
                    "content": "Because there's a cap there ,"
                }
            ]
        },
        {
            "query": "What did Project Manager recommend to do when discussing competitor information?",
            "oracle_info": [
                {
                    "turn_index": 171,
                    "sent_index": 0,
                    "speaker": "Project Manager",
                    "content": "No , actually ."
                },
                {
                    "turn_index": 171,
                    "sent_index": 1,
                    "speaker": "Project Manager",
                    "content": "That would be useful , though ,"
                },
                {
                    "turn_index": 177,
                    "sent_index": 3,
                    "speaker": "Marketing",
                    "content": "I just don't think of remote controls as somethin something people consciously assess in their purchasing habits ."
                }
            ]
        },
        {
            "query": "What did the group think of the importance of technology reasonable on the working design?",
            "oracle_info": [
                {
                    "turn_index": 228,
                    "sent_index": 0,
                    "speaker": "Marketing",
                    "content": "I remember when the first remote control my my family had was on a cable ."
                },
                {
                    "turn_index": 235,
                    "sent_index": 0,
                    "speaker": "Project Manager",
                    "content": "Maybe like a touch screen or something ?"
                },
                {
                    "turn_index": 241,
                    "sent_index": 0,
                    "speaker": "Project Manager",
                    "content": "It looks better ."
                },
                {
                    "turn_index": 244,
                    "sent_index": 0,
                    "speaker": "Marketing",
                    "content": "Um , nicer materials"
                }
            ]
        }
    ]
}