{
    "transcripts_id": "TS3006c",
    "general_query_list": [
        {
            "query": "Summarize the whole meeting.",
            "oracle_info": [
                {
                    "turn_index": 37,
                    "sent_index": 0,
                    "speaker": "Marketing",
                    "content": "Move to meeting room ."
                },
                {
                    "turn_index": 61,
                    "sent_index": 4,
                    "speaker": "Marketing",
                    "content": "Um this time about trendwatching ."
                },
                {
                    "turn_index": 63,
                    "sent_index": 5,
                    "speaker": "Marketing",
                    "content": "most important aspect for remote control happens to be a fancy look-and-feel . Instead of the current uh functional look-and-feel ."
                },
                {
                    "turn_index": 65,
                    "sent_index": 1,
                    "speaker": "Marketing",
                    "content": "And the third development um is that the remote control should be easy to use ."
                },
                {
                    "turn_index": 105,
                    "sent_index": 5,
                    "speaker": "Industrial Designer",
                    "content": "Well they gave me um an idea about what people want ."
                },
                {
                    "turn_index": 125,
                    "sent_index": 7,
                    "speaker": "Industrial Designer",
                    "content": "Uh the case materials ."
                },
                {
                    "turn_index": 161,
                    "sent_index": 0,
                    "speaker": "Industrial Designer",
                    "content": "So that's the end of it ."
                },
                {
                    "turn_index": 186,
                    "sent_index": 0,
                    "speaker": "Marketing",
                    "content": "Yeah with the programme ."
                },
                {
                    "turn_index": 220,
                    "sent_index": 4,
                    "speaker": "Project Manager",
                    "content": "Uh energy source , chip type , case type . And user interface ."
                },
                {
                    "turn_index": 224,
                    "sent_index": 0,
                    "speaker": "Marketing",
                    "content": "Rubber material ."
                },
                {
                    "turn_index": 236,
                    "sent_index": 0,
                    "speaker": "Industrial Designer",
                    "content": "to be able to m"
                },
                {
                    "turn_index": 287,
                    "sent_index": 1,
                    "speaker": "Project Manager",
                    "content": "'S the target group ."
                },
                {
                    "turn_index": 350,
                    "sent_index": 0,
                    "speaker": "Project Manager",
                    "content": "That's singly curved ."
                },
                {
                    "turn_index": 367,
                    "sent_index": 0,
                    "speaker": "Project Manager",
                    "content": "Yeah that would be an option ."
                },
                {
                    "turn_index": 477,
                    "sent_index": 0,
                    "speaker": "Industrial Designer",
                    "content": "That you , that it would be kind of shape like this , you know ."
                },
                {
                    "turn_index": 495,
                    "sent_index": 0,
                    "speaker": "Project Manager",
                    "content": "The female shape yeah ."
                },
                {
                    "turn_index": 573,
                    "sent_index": 0,
                    "speaker": "User Interface",
                    "content": "Yeah but the primary colours w we can uh create with the with the LEDs on the on the remote control ."
                },
                {
                    "turn_index": 603,
                    "sent_index": 0,
                    "speaker": "Project Manager",
                    "content": "Some yellow ."
                },
                {
                    "turn_index": 641,
                    "sent_index": 0,
                    "speaker": "Project Manager",
                    "content": "Like this ."
                },
                {
                    "turn_index": 747,
                    "sent_index": 0,
                    "speaker": "Project Manager",
                    "content": "Bit of light ."
                },
                {
                    "turn_index": 767,
                    "sent_index": 0,
                    "speaker": "Marketing",
                    "content": "Of the product ?"
                },
                {
                    "turn_index": 775,
                    "sent_index": 0,
                    "speaker": "Project Manager",
                    "content": "Yeah . Once they are finished . Yeah ."
                }
            ]
        }
    ],
    "specific_query_list": [
        {
            "query": "Summarize the personal presentations on the appearance design, the speak recognition system and the ideal materials of the remote control.",
            "oracle_info": [
                {
                    "turn_index": 2,
                    "sent_index": 0,
                    "speaker": "Marketing",
                    "content": "Yes , I made it ."
                },
                {
                    "turn_index": 28,
                    "sent_index": 0,
                    "speaker": "Marketing",
                    "content": "Or not ."
                },
                {
                    "turn_index": 63,
                    "sent_index": 8,
                    "speaker": "Marketing",
                    "content": "Um well it stands for the use of technical features that do not exist in current remote controls ."
                },
                {
                    "turn_index": 65,
                    "sent_index": 1,
                    "speaker": "Marketing",
                    "content": "And the third development um is that the remote control should be easy to use ."
                },
                {
                    "turn_index": 88,
                    "sent_index": 1,
                    "speaker": "Project Manager",
                    "content": "{vocalsound} Yeah you're just the user interface hmm ?"
                },
                {
                    "turn_index": 98,
                    "sent_index": 0,
                    "speaker": "Marketing",
                    "content": "Yeah . It's okay ."
                },
                {
                    "turn_index": 186,
                    "sent_index": 0,
                    "speaker": "Marketing",
                    "content": "Yeah with the programme ."
                },
                {
                    "turn_index": 217,
                    "sent_index": 2,
                    "speaker": "User Interface",
                    "content": "Um that was it ."
                },
                {
                    "turn_index": 235,
                    "sent_index": 0,
                    "speaker": "Project Manager",
                    "content": "Too {gap} ."
                },
                {
                    "turn_index": 346,
                    "sent_index": 0,
                    "speaker": "Project Manager",
                    "content": "Ah yeah bright colours ."
                },
                {
                    "turn_index": 367,
                    "sent_index": 0,
                    "speaker": "Project Manager",
                    "content": "Yeah that would be an option ."
                },
                {
                    "turn_index": 382,
                    "sent_index": 0,
                    "speaker": "Industrial Designer",
                    "content": "Yeah . As well ."
                },
                {
                    "turn_index": 421,
                    "sent_index": 0,
                    "speaker": "Industrial Designer",
                    "content": "I would draw it like this ."
                },
                {
                    "turn_index": 449,
                    "sent_index": 1,
                    "speaker": "Project Manager",
                    "content": "You could just make it mechanical ."
                }
            ]
        },
        {
            "query": "What did the Marketing think of the materials when giving personal presentations on the appearance design, the speak recognition system and the ideal materials of the remote control?",
            "oracle_info": [
                {
                    "turn_index": 105,
                    "sent_index": 4,
                    "speaker": "Industrial Designer",
                    "content": "That's why I had to , wanted to go first ."
                },
                {
                    "turn_index": 105,
                    "sent_index": 5,
                    "speaker": "Industrial Designer",
                    "content": "Well they gave me um an idea about what people want ."
                },
                {
                    "turn_index": 105,
                    "sent_index": 7,
                    "speaker": "Industrial Designer",
                    "content": "Uh I could not drag the pictures into the the slides so s so I don't have examples of how it looks like ."
                },
                {
                    "turn_index": 105,
                    "sent_index": 10,
                    "speaker": "Industrial Designer",
                    "content": "and shapes that are curved and not uh solid straight lines anymore ."
                },
                {
                    "turn_index": 108,
                    "sent_index": 0,
                    "speaker": "Industrial Designer",
                    "content": "There's a lot of options that we have to discuss ."
                },
                {
                    "turn_index": 108,
                    "sent_index": 4,
                    "speaker": "Industrial Designer",
                    "content": "which we yeah we Dutch refer to it as the kneipgatt ."
                },
                {
                    "turn_index": 112,
                    "sent_index": 0,
                    "speaker": "Industrial Designer",
                    "content": "Which will be fun for toddlers right , if they wanna use the {disfmarker}"
                }
            ]
        },
        {
            "query": "What did the Industrial Designer recommend to do when discussing personal presentations on the appearance design, the speak recognition system and the ideal materials of the remote control?",
            "oracle_info": [
                {
                    "turn_index": 331,
                    "sent_index": 0,
                    "speaker": "Industrial Designer",
                    "content": "Personally I think it's really ugly ."
                },
                {
                    "turn_index": 335,
                    "sent_index": 0,
                    "speaker": "Industrial Designer",
                    "content": "Just give me the thing that it's inside there {gap}"
                }
            ]
        },
        {
            "query": "What did the group talk about the shape, the color and the front buttons of the remote control?",
            "oracle_info": [
                {
                    "turn_index": 495,
                    "sent_index": 0,
                    "speaker": "Project Manager",
                    "content": "The female shape yeah ."
                },
                {
                    "turn_index": 512,
                    "sent_index": 0,
                    "speaker": "Industrial Designer",
                    "content": "You know kind of thing ."
                },
                {
                    "turn_index": 526,
                    "sent_index": 0,
                    "speaker": "Industrial Designer",
                    "content": "I would do the arrows here , kind of thing ."
                },
                {
                    "turn_index": 527,
                    "sent_index": 0,
                    "speaker": "Marketing",
                    "content": "Spongey can be reached by means of {disfmarker}"
                },
                {
                    "turn_index": 544,
                    "sent_index": 0,
                    "speaker": "Marketing",
                    "content": "Uh pretty nice design . Yeah . {vocalsound}"
                },
                {
                    "turn_index": 567,
                    "sent_index": 0,
                    "speaker": "Marketing",
                    "content": "with very uh bright tones I guess ."
                },
                {
                    "turn_index": 573,
                    "sent_index": 0,
                    "speaker": "User Interface",
                    "content": "Yeah but the primary colours w we can uh create with the with the LEDs on the on the remote control ."
                },
                {
                    "turn_index": 603,
                    "sent_index": 0,
                    "speaker": "Project Manager",
                    "content": "Some yellow ."
                },
                {
                    "turn_index": 627,
                    "sent_index": 1,
                    "speaker": "Marketing",
                    "content": "That would be a nice uh nice device I guess ."
                },
                {
                    "turn_index": 700,
                    "sent_index": 0,
                    "speaker": "Marketing",
                    "content": "And then time was up ."
                },
                {
                    "turn_index": 711,
                    "sent_index": 0,
                    "speaker": "Marketing",
                    "content": "That should be pretty nice colour ."
                },
                {
                    "turn_index": 720,
                    "sent_index": 0,
                    "speaker": "Industrial Designer",
                    "content": "They will see one of each as grey ."
                },
                {
                    "turn_index": 728,
                    "sent_index": 0,
                    "speaker": "Project Manager",
                    "content": "You can make them red ."
                },
                {
                    "turn_index": 746,
                    "sent_index": 0,
                    "speaker": "Marketing",
                    "content": "So just an extra"
                },
                {
                    "turn_index": 758,
                    "sent_index": 0,
                    "speaker": "Industrial Designer",
                    "content": "as the colour the {vocalsound} {disfmarker}"
                },
                {
                    "turn_index": 767,
                    "sent_index": 0,
                    "speaker": "Marketing",
                    "content": "Of the product ?"
                }
            ]
        },
        {
            "query": "Why did the Marketing disagree with the Industrial Designer when discussing the shape, the color and the front buttons of the remote control?",
            "oracle_info": [
                {
                    "turn_index": 528,
                    "sent_index": 0,
                    "speaker": "Industrial Designer",
                    "content": "Those buttons ? And the simple buttons here ,"
                },
                {
                    "turn_index": 531,
                    "sent_index": 0,
                    "speaker": "Industrial Designer",
                    "content": "so that {disfmarker}"
                },
                {
                    "turn_index": 533,
                    "sent_index": 1,
                    "speaker": "Marketing",
                    "content": "And and the and the control thngs in the middle ? The the the arrows ?"
                }
            ]
        },
        {
            "query": "What did the User Interface elaborate on the shape of the button?",
            "oracle_info": [
                {
                    "turn_index": 774,
                    "sent_index": 1,
                    "speaker": "Marketing",
                    "content": "Or you you or you send it to me ."
                },
                {
                    "turn_index": 774,
                    "sent_index": 2,
                    "speaker": "Marketing",
                    "content": "Or just {disfmarker}"
                },
                {
                    "turn_index": 777,
                    "sent_index": 0,
                    "speaker": "Project Manager",
                    "content": "Yeah but maybe you can do the evaluation {disfmarker} you don't have to evaluate yet but you can make a procedure which to follow ."
                }
            ]
        }
    ]
}