{
    "transcripts_id": "TS3007b",
    "general_query_list": [
        {
            "query": "Summarize the whole meeting.",
            "oracle_info": [
                {
                    "turn_index": 17,
                    "sent_index": 7,
                    "speaker": "Project Manager",
                    "content": "Uh the remote control shou should onl only be used for the television ,"
                },
                {
                    "turn_index": 17,
                    "sent_index": 8,
                    "speaker": "Project Manager",
                    "content": "so it uh not gonna it's not gonna be a multi-purpose remote control ,"
                },
                {
                    "turn_index": 20,
                    "sent_index": 2,
                    "speaker": "Project Manager",
                    "content": "but with this uh new remote uh they uh will uh {disfmarker} would like to reach uh a group uh younger than uh forty ."
                },
                {
                    "turn_index": 27,
                    "sent_index": 4,
                    "speaker": "Marketing",
                    "content": "that's what you do with a remote control ."
                },
                {
                    "turn_index": 29,
                    "sent_index": 0,
                    "speaker": "Marketing",
                    "content": "Yeah , okay ."
                },
                {
                    "turn_index": 39,
                    "sent_index": 0,
                    "speaker": "Marketing",
                    "content": "where you can put the the remote control in ."
                },
                {
                    "turn_index": 54,
                    "sent_index": 0,
                    "speaker": "Marketing",
                    "content": "Just for the minor functions perhaps ."
                },
                {
                    "turn_index": 58,
                    "sent_index": 2,
                    "speaker": "Marketing",
                    "content": "that's it ."
                },
                {
                    "turn_index": 60,
                    "sent_index": 24,
                    "speaker": "Industrial Designer",
                    "content": "that wouldn't mean a a cheap uh remote control for us ."
                },
                {
                    "turn_index": 69,
                    "sent_index": 8,
                    "speaker": "Industrial Designer",
                    "content": "I figured that would be best ,"
                },
                {
                    "turn_index": 79,
                    "sent_index": 5,
                    "speaker": "Industrial Designer",
                    "content": "we shouldn't make a big uh remote control for simple functions ,"
                },
                {
                    "turn_index": 106,
                    "sent_index": 6,
                    "speaker": "User Interface",
                    "content": "So just keep it simple ,"
                },
                {
                    "turn_index": 151,
                    "sent_index": 2,
                    "speaker": "User Interface",
                    "content": "keep it simple ."
                },
                {
                    "turn_index": 163,
                    "sent_index": 0,
                    "speaker": "User Interface",
                    "content": "and maybe use a touch screen ,"
                },
                {
                    "turn_index": 167,
                    "sent_index": 0,
                    "speaker": "Industrial Designer",
                    "content": "The extra functions ."
                },
                {
                    "turn_index": 201,
                    "sent_index": 0,
                    "speaker": "Marketing",
                    "content": "Yeah , of course ."
                },
                {
                    "turn_index": 206,
                    "sent_index": 1,
                    "speaker": "Marketing",
                    "content": "I had another uh idea about maybe parental control . Um ,"
                },
                {
                    "turn_index": 293,
                    "sent_index": 0,
                    "speaker": "Marketing",
                    "content": "Yeah , yeah , some of them ."
                },
                {
                    "turn_index": 316,
                    "sent_index": 0,
                    "speaker": "Industrial Designer",
                    "content": "I actually use one of those"
                },
                {
                    "turn_index": 342,
                    "sent_index": 0,
                    "speaker": "Industrial Designer",
                    "content": "Yeah . Yeah , that would be possible . Yeah , sure ."
                },
                {
                    "turn_index": 360,
                    "sent_index": 0,
                    "speaker": "User Interface",
                    "content": "Firmware update , you say ."
                },
                {
                    "turn_index": 377,
                    "sent_index": 0,
                    "speaker": "Industrial Designer",
                    "content": "Yeah , maybe something like service cen"
                },
                {
                    "turn_index": 510,
                    "sent_index": 0,
                    "speaker": "Marketing",
                    "content": "Yeah , of course ."
                }
            ]
        }
    ],
    "specific_query_list": [
        {
            "query": "What did Project Manager mention when giving general arrangements at the very beginning of the meeting?",
            "oracle_info": [
                {
                    "turn_index": 17,
                    "sent_index": 1,
                    "speaker": "Project Manager",
                    "content": "but there were four points"
                },
                {
                    "turn_index": 17,
                    "sent_index": 3,
                    "speaker": "Project Manager",
                    "content": "First one is uh they think that uh teletext teletext becomes outdated"
                },
                {
                    "turn_index": 17,
                    "sent_index": 4,
                    "speaker": "Project Manager",
                    "content": "uh and internet will be the the main uh focus ."
                },
                {
                    "turn_index": 17,
                    "sent_index": 7,
                    "speaker": "Project Manager",
                    "content": "Uh the remote control shou should onl only be used for the television ,"
                },
                {
                    "turn_index": 17,
                    "sent_index": 8,
                    "speaker": "Project Manager",
                    "content": "so it uh not gonna it's not gonna be a multi-purpose remote control ,"
                },
                {
                    "turn_index": 20,
                    "sent_index": 2,
                    "speaker": "Project Manager",
                    "content": "but with this uh new remote uh they uh will uh {disfmarker} would like to reach uh a group uh younger than uh forty ."
                }
            ]
        },
        {
            "query": "What did Marketing discuss about improving new remote control features based on the questionnaire?",
            "oracle_info": [
                {
                    "turn_index": 25,
                    "sent_index": 17,
                    "speaker": "Marketing",
                    "content": "First point is , seventy five percent of the users find the most repo remote controls very ugly ,"
                },
                {
                    "turn_index": 25,
                    "sent_index": 21,
                    "speaker": "Marketing",
                    "content": "third findings ."
                },
                {
                    "turn_index": 37,
                    "sent_index": 3,
                    "speaker": "Marketing",
                    "content": "I think we should aim at the uh audience from sixteen to forty five ."
                },
                {
                    "turn_index": 46,
                    "sent_index": 1,
                    "speaker": "Marketing",
                    "content": "they have to be on it"
                },
                {
                    "turn_index": 50,
                    "sent_index": 0,
                    "speaker": "Marketing",
                    "content": "but um the most used buttons uh have to be bigger or {disfmarker}"
                },
                {
                    "turn_index": 54,
                    "sent_index": 0,
                    "speaker": "Marketing",
                    "content": "Just for the minor functions perhaps ."
                },
                {
                    "turn_index": 56,
                    "sent_index": 0,
                    "speaker": "Marketing",
                    "content": "Just to get less buttons on the remote control , to make it easier and quicker to learn ."
                }
            ]
        },
        {
            "query": "What did Industrial Designer think of the remote control with Bluetooth and other new technology when discussing the possibility of applying different technologies?",
            "oracle_info": [
                {
                    "turn_index": 60,
                    "sent_index": 17,
                    "speaker": "Industrial Designer",
                    "content": "not like all probably know ."
                },
                {
                    "turn_index": 60,
                    "sent_index": 20,
                    "speaker": "Industrial Designer",
                    "content": "that's also focused on infrared ,"
                },
                {
                    "turn_index": 60,
                    "sent_index": 21,
                    "speaker": "Industrial Designer",
                    "content": "so if we want to uh build uh mm a remote control uh with Bluetooth for instance then uh the T_V_ should have Bluetooth too in order to communicate ,"
                },
                {
                    "turn_index": 60,
                    "sent_index": 22,
                    "speaker": "Industrial Designer",
                    "content": "so that would mean extra cost for the user"
                },
                {
                    "turn_index": 60,
                    "sent_index": 24,
                    "speaker": "Industrial Designer",
                    "content": "that wouldn't mean a a cheap uh remote control for us ."
                },
                {
                    "turn_index": 69,
                    "sent_index": 3,
                    "speaker": "Industrial Designer",
                    "content": "But it may be uh may be something to explore ."
                },
                {
                    "turn_index": 69,
                    "sent_index": 10,
                    "speaker": "Industrial Designer",
                    "content": "So we didn't {disfmarker} and we don't have to do all uh {disfmarker} to be too complicated about that ."
                },
                {
                    "turn_index": 69,
                    "sent_index": 28,
                    "speaker": "Industrial Designer",
                    "content": "and then it's sent to the infrared bulb"
                }
            ]
        },
        {
            "query": "What did Industrial Designer propose to build a new remote control when discussing the Bluetooth technology and the functions of remote control?",
            "oracle_info": [
                {
                    "turn_index": 60,
                    "sent_index": 6,
                    "speaker": "Industrial Designer",
                    "content": "how they worked ,"
                },
                {
                    "turn_index": 60,
                    "sent_index": 8,
                    "speaker": "Industrial Designer",
                    "content": "and how they are connected together ."
                },
                {
                    "turn_index": 60,
                    "sent_index": 12,
                    "speaker": "Industrial Designer",
                    "content": "and how we could uh build one"
                },
                {
                    "turn_index": 60,
                    "sent_index": 23,
                    "speaker": "Industrial Designer",
                    "content": "and thus uh that's"
                },
                {
                    "turn_index": 60,
                    "sent_index": 25,
                    "speaker": "Industrial Designer",
                    "content": "So that's probably why most controls are still infrared ."
                },
                {
                    "turn_index": 69,
                    "sent_index": 8,
                    "speaker": "Industrial Designer",
                    "content": "I figured that would be best ,"
                },
                {
                    "turn_index": 69,
                    "sent_index": 43,
                    "speaker": "Industrial Designer",
                    "content": "no input from the television ."
                },
                {
                    "turn_index": 79,
                    "sent_index": 5,
                    "speaker": "Industrial Designer",
                    "content": "we shouldn't make a big uh remote control for simple functions ,"
                },
                {
                    "turn_index": 79,
                    "sent_index": 6,
                    "speaker": "Industrial Designer",
                    "content": "but we we should stick to the basics ."
                }
            ]
        },
        {
            "query": "What did User Interface think about the features of the new remote control when discussing the technical functions of the design and usability functions?",
            "oracle_info": [
                {
                    "turn_index": 153,
                    "sent_index": 2,
                    "speaker": "User Interface",
                    "content": "or at least putting them somewhere on the remote where they're not in the way for the for the most important functions ."
                },
                {
                    "turn_index": 154,
                    "sent_index": 5,
                    "speaker": "Marketing",
                    "content": "because one the one hand uh you make the remote control compatible for elder users just by uh scaling up the pictures or something ."
                },
                {
                    "turn_index": 157,
                    "sent_index": 0,
                    "speaker": "User Interface",
                    "content": "Maybe that's an option ."
                },
                {
                    "turn_index": 157,
                    "sent_index": 2,
                    "speaker": "User Interface",
                    "content": "Uh make a remote that fits easily in the hands"
                },
                {
                    "turn_index": 166,
                    "sent_index": 0,
                    "speaker": "Marketing",
                    "content": "then what's gonna be displayed on the touch screen ?"
                },
                {
                    "turn_index": 183,
                    "sent_index": 1,
                    "speaker": "User Interface",
                    "content": "keep the buttons always available"
                },
                {
                    "turn_index": 186,
                    "sent_index": 0,
                    "speaker": "User Interface",
                    "content": "and use the lower part of the touch screen for the rest ."
                }
            ]
        },
        {
            "query": "What did the group discuss at the end of the meeting when summarizing the whole meeting?",
            "oracle_info": [
                {
                    "turn_index": 289,
                    "sent_index": 7,
                    "speaker": "Project Manager",
                    "content": "we must keep it simple ,"
                },
                {
                    "turn_index": 289,
                    "sent_index": 8,
                    "speaker": "Project Manager",
                    "content": "but have the opportunity to uh have more options"
                },
                {
                    "turn_index": 289,
                    "sent_index": 14,
                    "speaker": "Project Manager",
                    "content": "the functions , know , like the menus or the the parental control must be all uh by the {disfmarker} done by the remote control and not by the television ."
                },
                {
                    "turn_index": 295,
                    "sent_index": 1,
                    "speaker": "Marketing",
                    "content": "but that's not possible ."
                },
                {
                    "turn_index": 304,
                    "sent_index": 0,
                    "speaker": "User Interface",
                    "content": "and they all have a functionality for all the T_V_s ,"
                },
                {
                    "turn_index": 308,
                    "sent_index": 0,
                    "speaker": "Marketing",
                    "content": "But {disfmarker}"
                },
                {
                    "turn_index": 314,
                    "sent_index": 0,
                    "speaker": "Industrial Designer",
                    "content": "and that that is bit of a tricky job ."
                },
                {
                    "turn_index": 326,
                    "sent_index": 0,
                    "speaker": "User Interface",
                    "content": "In codes , y you you get a b a book with codes ."
                },
                {
                    "turn_index": 336,
                    "sent_index": 0,
                    "speaker": "User Interface",
                    "content": "Memory in the in the remote ."
                },
                {
                    "turn_index": 355,
                    "sent_index": 0,
                    "speaker": "Project Manager",
                    "content": "We have five minutes to go ."
                },
                {
                    "turn_index": 356,
                    "sent_index": 2,
                    "speaker": "User Interface",
                    "content": "it's very good for marketing"
                },
                {
                    "turn_index": 357,
                    "sent_index": 0,
                    "speaker": "Marketing",
                    "content": "New remote ?"
                },
                {
                    "turn_index": 367,
                    "sent_index": 3,
                    "speaker": "Industrial Designer",
                    "content": "the most most people have ,"
                },
                {
                    "turn_index": 394,
                    "sent_index": 0,
                    "speaker": "Marketing",
                    "content": "I I think it's uh most cheap or cheapest to just do the updates uh at the service centre or at the shop ."
                },
                {
                    "turn_index": 417,
                    "sent_index": 1,
                    "speaker": "User Interface",
                    "content": "I was uh doubting about which one to take ,"
                }
            ]
        }
    ]
}